<?xml version="1.0" encoding="utf-8" ?>

<ui namespace="ProfileCell_iPhone">
    
    <linear orientation="v" class="wrapper">
        
        <linear orientation="v" class="header-wrapper">
            <image id="bg" class="bg"/>
			<linear orientation="v" class="header-box">
                <linear orientation="v" class="header-avatar-box">
                    <image id="header-avatar" class="header-avatar"/>
                    <image id="header-avatar-head-icon" class="header-avatar-head-icon"/>
                    
					<button id="carema"/>
                    <label id="name" class="header-name"></label>
                </linear>
                <!--
                <label id="header_money_bg"></label>
                <label id="header_money_name">余额</label>
                <label id="header_money_value">￥0</label>
                <button id="header_money_button"></button>
                
                <label id="header_score_bg"></label>
                <label id="header_score_name">积分</label>
                <label id="header_score_value">0</label>
                <button id="header_score_button"></button>
                 -->
                <label id="lblenterofhighmember" class="lblenterofhighmember">成为爱高会员></label>
                <button id="btnenterofhighmember" class="lblenterofhighmember"></button>
                
                <linear orientation="h" class="header-level-box">
                    <image id="header-level-icon"/>
                    <label id="header-level-name"/>
                </linear>
            </linear>
			<button id="signin"></button>
        </linear>
        
        <linear orientation="v" class="scroll-wrapper">
            
            <linear orientation="h" class="bar-wrapper">
                <image class="list-large-bg"/>
                <linear orientation="v" class="bar-item" id="123">
                    <label id="header_money_value" class="balancevalue">￥0</label>
                    <label id="header_money_name" class="balancetitle">余额</label>
                    <!--<button id="header_money_button" class="fill"/>-->
                </linear>
                
                <linear orientation="v" class="bar-item" id="321">
                    <label id="header_score_value" class="jifenvalue">5000</label>
                    <label id="header_score_name" class="jifentitle">积分</label>
                    <!--<button id="header_score_button" class="fill"/>-->
                </linear>
                
                <linear orientation="v" class="bar-item">
                    <label class="bar-item-info recharge">充值</label>
                    <button id="recharge" class="fill"/>
                </linear>
                
                <linear orientation="v" class="bar-item">
                    <label class="bar-item-info pay">支付</label>
                    <button id="pay" class="fill"/>
                </linear>
            </linear>




                        <linear orientation="h" class="bar-wrapper">
                            <image class="list-large-bg"/>
                            <linear orientation="v" class="bar-item">
                                <image class="bar-item-icon payment"/>
                                <label class="bar-item-info" id="await_pay_label">待付款 商品</label>
                                <linear orientation="v" class="badge-wrapper">
                                    <image id="await_pay-bg" class="badge-wrapper-bg"/>
                                    <label id="await_pay" class="bar-item-badge"></label>
                                </linear>
                                <button id="order_await_pay" class="fill"/>
                            </linear>
                            
                            <linear orientation="v" class="bar-item">
                                <image class="bar-item-icon ship" />
                                <label class="bar-item-info" id="await_ship_label">待发货 商品</label>
                                <linear orientation="v" class="badge-wrapper">
                                    <image id="await_ship-bg" class="badge-wrapper-bg"/>
                                    <label id="await_ship" class="bar-item-badge"></label>
                                </linear>
                                <button id="order_await_ship" class="fill"/>
                            </linear>
                            
                            <linear orientation="v" class="bar-item">
                                <image class="bar-item-icon receipt"/>
                                <label class="bar-item-info" id="shipped_label">待收货 商品</label>
                                <linear orientation="v" class="badge-wrapper">
                                    <image id="shipped-bg" class="badge-wrapper-bg"/>
                                    <label id="shipped" class="bar-item-badge"></label>
                                </linear>
                                <button id="order_shipped" class="fill"/>
                            </linear>
                            
                            <linear orientation="v" class="bar-item">
                                <image class="bar-item-icon history"/>
                                <label class="bar-item-info" id="finished_label">购物历史</label>
                                <linear orientation="v" class="badge-wrapper">
                                    <image id="finished-bg" class="badge-wrapper-bg"/>
                                    <label id="finished" class="bar-item-badge"></label>
                                </linear>
                                <button id="order_finished" class="fill"/>
                            </linear>
                        </linear>
            
            <linear orientation="v" class="list-wrapper">
                
                <linear id="orders_list_item" orientation="h" class="list-item">
                    <image class="list-bg"/>
                    <label class="list-title">历史订场</label>
                    <label id="order-count" class="list-subtitle">0</label>
                    <image class="list-indictor"/>
                    <button id="orders_list" class="fill"/>
                </linear>
                
                <linear id="collection_list_item" orientation="h" class="list-item">
                    <image class="list-bg"/>
                    <label class="list-title">我的收藏</label>
                    <label id="fav-count" class="list-subtitle">0</label>
                    <image class="list-indictor"/>
                    <button id="collection" class="fill"/>
                </linear>
                
                <linear id="notification_list_item" orientation="h" class="list-item">
                    <image class="list-bg"/>
                    <label class="list-title">消息列表</label>
                    <label class="list-subtitle"></label>
                    <image class="list-indictor"/>
                    <button id="notification" class="fill"/>
                </linear>
                
                <linear id="change_password_list_item" orientation="h" class="list-item">
                    <image class="list-bg"/>
                    <label class="list-title">修改密码</label>
                    <label class="list-subtitle"></label>
                    <image class="list-indictor"/>
                    <button id="change_password" class="fill"/>
                </linear>
                
                <linear id="manage_list_item" orientation="h" class="list-item">
                    <image class="list-bg"/>
                    <label class="list-title">@{manage_address}</label>
                    <label class="list-subtitle"></label>
                    <image class="list-indictor"/>
                    <button id="manage" class="fill"/>
                </linear>
                
                <linear id="help_list_item" orientation="h" class="list-item">
                    <image class="list-bg"/>
                    <label class="list-title">帮助</label>
                    <label class="list-subtitle"></label>
                    <image class="list-indictor"/>
                    <button id="help" class="fill"/>
                </linear>
                
                <linear id="new_version_list_item" orientation="h" class="list-item">
                    <image class="list-bg"/>
                    <label class="list-title">当前版本</label>
                    <label id="current-version" class="list-subtitle"></label>
                    <button id="new_version" class="fill"/>
                </linear>
                
                <linear id="logout_list_item" orientation="h" class="list-item">
                    <image class="list-bg"/>
                    <label class="list-title">退出当前账户</label>
                    <label class="list-subtitle"></label>
                    <button id="logout" class="fill"/>
                </linear>
                
                <linear orientation="h" class="list-item-qrcode">
                    <image class="list-qrcode"/>
                </linear>
                
            </linear>
            
        </linear>
    </linear>
    
    <style type="text/css">
        
        .lblenterofhighmember {
        color: #FF0000;
        width: 120px;
        height: 25px;
        position: absolute !important;
        font-size: 18px;
        text-align: left;
        font-weight: bold;
        top:100px;
        left:150px;
        }
        
        
        .recharge
        {
        margin-top:10px;
        font-size: 16px;
        font-weight: bold;
        }
        
        .pay
        {
        margin-top:10px;
        font-size: 16px;
        font-weight: bold;
        }
        
        .balancetitle
        {
        height:auto;
        line-num:1;
        text-align:center;
        font-size: 16px;
        font-weight: bold;
        }
        
        .balancevalue
        {
        margin-top:15px;
        text-align:center;
        height:auto;
        line-num:1;
        color:#FF0000;
        font-size: 16px;
        font-weight: bold;
        }
        
        .jifentitle
        {
        font-size: 16px;
        font-weight: bold;
        height:auto;
        line-num:1;
        text-align:center;
        }
        
        .jifenvalue
        {
        font-size: 16px;
        font-weight: bold;
        margin-top:15px;
        text-align:center;
        height:auto;
        line-num:1;
        }


        .fill {
            width: 100%;
            height: 100%;
            position: absolute !important;
            top: 0;
            left: 0;
        }
        
        .wrapper {
            height: auto;
            width: 100%;
        }
        
        .scroll-wrapper {
            height: auto;
            margin-bottom: 20px;
            align: center;
        }
        
        .list-wrapper {
            align: center;
            height: auto;
        }
        
        .unlogin {
            align: center;
            height: auto;
        }
        
        .login {
            align: center;
            height: auto;
        }
        
        .list-item {
            margin-top: 10px;
            width: 300px;
            height: 44px;
            v-align: center;
        }
        
        .list-title {
            margin-left: 14px;
            font-size: 20px;
			font-weight: bold;
            color: #333;
            width: 146px;
            text-align: left;
            height: 20px;
        }
        
        .list-subtitle {
            font-size: 20px;
			font-weight: lighter;
            color: #333;
            margin: 0 10px;
            width: 100px;
            text-align: right;
            height: 20px;
        }
        
        
        .list-item-qrcode {
        margin-top: 10px;
        width: 135px;
        height: 135px;
        v-align: center;
        }
        
        .list-qrcode {
        width: 135px;
        height: 135px;
        position: absolute !important;
        image: url(qrcode.png) !important;
        image-insets: 10;
        image-mode: fit;
        }
        
        .list-indictor {
            width: auto;
            height: 100%;
            image: url(accsessory-arrow-right.png);
        }
        
        .bar-wrapper {
            width: 300px;
            height: 70px;
            v-align: center;
            margin-top: 10px;
            padding-left:10px;
        }
        
        .bar-item {
            width: 60px;
            height: 60px;
            align: center;
            margin-left: 10px;
            background-color:#000000;
        }
        
        .badge-wrapper {
            width: auto;
            height: 15px;
            position: absolute;
			left: 36px;
			top: 0px;
        }

        .badge-wrapper-bg {
            width: 100%;
            height: 100%;
            position: absolute !important;
            top: 0;
            left: 0;
            image-mode: stretch;
            image-src: url(search-new-shopping-cart-num-bg.png);
        }
        
        .bar-item-badge {
            color: white;
            width: auto;
            height: 100%;
            text-align: center;
            line-height: 13px;
            font-size: 10px;
			font-weight: bold;
			margin-left: 5px;
			margin-right: 5px;
        }
        
        .bar-item-icon {
            width: 20px;
            height: 20px;
        }
        
        .payment {
            background-image: url(profile-refresh-payment-icon.png);
        }
        
        .ship {
            background-image: url(profile-refresh-ship-icon.png);
        }
        
        .receipt {
            background-image: url(profile-refresh-receipt-icon.png);
        }
        
        .history {
            background-image: url(profile-refresh-history-icon.png);
        }
        
        .bar-item-info {
            text-align: center;
			font-size: 16px;
			font-weight: bold;
            color: #333;
            width: 100%;
            height: 40px;
            line-num: 2;
        }
        
        .header-wrapper {
            width: 100%;
            height: 134px;
            v-align: center;
        }
        
        .header-box {
            margin-left: 20px;
            width: 280px;
            height: 150px;
            align: center;
        }
        
        .header-setting {
            width: 21px;
            height: 21px;
            background-image: url(profile-refresh-site-icon.png);
            float: right;
            margin-right: 20px;
        }
        
        .header-avatar-box {
        left:20px
            width: 135px;
            height: 100px;
            v-align: bottom;
            margin-top: 30px;
        }

        .header-avatar {
            width: 135px;
            height: 100px;
            position: absolute !important;
            top: 0;
            left: 0;
            image-mode: fill;
			image-style: round;
            border: 5px solid #ffffff;
        }
        
        .header-avatar-head-icon {
        width: 60px;
        height: 60px;
        position: absolute !important;
        top: 0;
        left: 40px;
        border-radius: 30px;
        image-mode: fill;
        image-style: round;
        border: 5px solid #ffffff;
        }

        .header-level-box {
			width: auto;
			height: 24px;
        }

        #header-level-icon {
			margin-top: 8px;
			height: 14px;
			width: 11px;
			margin-right: 5px;
        }

        #header-level-name {
			background-color: #333 0.6;
			border-radius: 3px;
			color: #ccc;
			width:auto;
			height: 16px;
			font-size: 13px;
			font-weight: bold;
			margin-top: 5px;
        }

        .header-carema {
            width: 24px;
            height: 24px;
            float: right;
            background-image: url(profile-refresh-camera-icon.png);
        }

        .header-name {
        position: absolute !important;
            font-size: 18px;
            font-weight: bold;
            color: #222222;
            
            width: auto;
            height: auto;
            text-align: center;
            left: 15px;
            margin: 0px;
            top : 65px;
            align : center;
            v-align: top;
            line-num: 2;
        }

		#signin {
			position: absolute;
			left: 0px;
			top: 0px;
            width: 100%;
            height: 100%;
		}

        .body-bg {
            width: 100%;
            height: 100%;
            position: absolute !important;
            top: 0;
            left: 0;
            background-color: #999999;
            background-mode: stretch;
            background-insets: 10px;
            background-image: url(body-bg.png);
        }
        
        .list-bg {
            width: 100%;
            height: 100%;
            position: absolute !important;
            top: 0;
            left: 0;
            image: url(item-graph-cont-box-bg.png) !important;
            image-insets: 10;
            image-mode: fit;
        }

        .list-large-bg {
            width: 100%;
            height: 100%;
            position: absolute !important;
            top: 0;
            left: 0;
            image: url(body-cont-bg.png) !important;
            image-insets: 10 25;
            image-mode: fit;
        }

        .bg {
            width: 100%;
            height: 100%;
            position: absolute !important;
            top: 0;
            left: 0;
            background-color: #eeeeee;
            image-src:url(profile_img_bg.png);
        }
        
        .container {
            background-color: #aaa;
        }

		#carema {
			width: 100%;
			height: 100%;
            position: absolute !important;
            top: 0;
            left: 0;
		}
        
        </style>
</ui>